qq_training_wheels/__init__.py
qq_training_wheels/momentum_trading.py
qq_training_wheels-0.0.1.dist-info/LICENSE
qq_training_wheels-0.0.1.dist-info/METADATA
qq_training_wheels-0.0.1.dist-info/WHEEL
qq_training_wheels-0.0.1.dist-info/top_level.txt
qq_training_wheels-0.0.1.dist-info/RECORD
