Metadata-Version: 2.1
Name: qq-training-wheels
Version: 0.0.1
Summary: Getting started with some basic functionalities of Quant Quest
Home-page: https://github.com/pypa/qq_training_wheels
Author: Shashank Yadav
Author-email: shashank@auquan.com
License: UNKNOWN
Platform: UNKNOWN
Classifier: Programming Language :: Python :: 3
Classifier: License :: OSI Approved :: MIT License
Classifier: Operating System :: OS Independent
Requires-Python: >=3.6
